{"imagePath":"Caveman_tex.png","width":128,"height":256,"name":"Caveman","SubTexture":[{"width":22,"y":164,"height":34,"name":"000","x":1},{"width":106,"y":1,"height":84,"name":"001","x":1},{"width":25,"y":132,"height":44,"name":"002","x":86},{"width":57,"y":87,"height":75,"name":"003","x":1},{"width":25,"y":178,"height":44,"name":"004","x":86},{"width":24,"y":132,"height":50,"name":"005","x":60},{"width":49,"y":87,"height":43,"name":"006","x":60},{"width":18,"y":1,"height":16,"name":"007","x":109}]}